{
  "_fv": 34,
  "_type": "potion",
  "definition": {
    "potionName": "Activated Strange Bottle",
    "splashName": "Splash Activated Strange Bottle",
    "lingeringName": "Lingering Activated Strange Bottle",
    "arrowName": "Arrow of Activated Strange Bottle",
    "effects": [
      {
        "effect": {
          "value": "SLOWNESS"
        },
        "duration": 3600,
        "amplifier": 2,
        "ambient": false,
        "showParticles": true
      },
      {
        "effect": {
          "value": "BLINDNESS"
        },
        "duration": 3600,
        "amplifier": 2,
        "ambient": false,
        "showParticles": true
      },
      {
        "effect": {
          "value": "MINING_FATIGUE"
        },
        "duration": 3600,
        "amplifier": 2,
        "ambient": false,
        "showParticles": true
      }
    ]
  }
}