{
  "_fv": 34,
  "_type": "tag",
  "definition": {
    "type": "Blocks",
    "items": [],
    "blocks": [
      {
        "value": "CUSTOM:Darkmatterbrickswall"
      },
      {
        "value": "CUSTOM:Darkmattertileswalls"
      },
      {
        "value": "CUSTOM:PolishedDarkMatterWall"
      },
      {
        "value": "CUSTOM:TwistedMatterBricksWall"
      },
      {
        "value": "CUSTOM:TwistedMatterTilesWall"
      },
      {
        "value": "CUSTOM:PolishedTwistedMatterWall"
      }
    ],
    "functions": [],
    "entities": [],
    "biomes": [],
    "name": "walls",
    "namespace": "minecraft"
  }
}